LICENSE
setup.py
CGWPY.egg-info/PKG-INFO
CGWPY.egg-info/SOURCES.txt
CGWPY.egg-info/dependency_links.txt
CGWPY.egg-info/requires.txt
CGWPY.egg-info/top_level.txt
cgwpy/__init__.py
cgwpy/analysis.py
cgwpy/modelisation.py
cgwpy/tools.py
cgwpy.egg-info/PKG-INFO
cgwpy.egg-info/SOURCES.txt
cgwpy.egg-info/dependency_links.txt
cgwpy.egg-info/requires.txt
cgwpy.egg-info/top_level.txt