Metadata-Version: 2.1
Name: cgwpy
Version: 0.2.44
Summary: Continuous Gravitational Waves library toolkit
Author: Jules Perret
License: MIT
Platform: UNKNOWN
License-File: LICENSE
